coiextract/__init__.py
coiextract/extract.py
coiextract-0.1.0.dist-info/METADATA
coiextract-0.1.0.dist-info/WHEEL
coiextract-0.1.0.dist-info/RECORD
